README.md
setup.py
debug_world/__init__.py
debug_world/print_str.py
python_hello.egg-info/PKG-INFO
python_hello.egg-info/SOURCES.txt
python_hello.egg-info/dependency_links.txt
python_hello.egg-info/requires.txt
python_hello.egg-info/top_level.txt